tfwr_expand/__builtins__.py
tfwr_expand/__init__.py
tfwr_expand/_tfwr_official_provided.__builtins__.py
tfwr_expand/algorithms.py
tfwr_expand/tools.py
tfwr_expand-0.1.1.dist-info/licenses/LICENSE
tfwr_expand-0.1.1.dist-info/WHEEL
tfwr_expand-0.1.1.dist-info/METADATA
tfwr_expand-0.1.1.dist-info/RECORD
