Metadata-Version: 2.4
Name: tfwr-expand
Version: 0.1.1
Summary: A library for The Farmer Was Replaced.
Author: Orange 233
Author-email: Orange 233 <orange_233@foxmail.com>
License-Expression: MIT
License-File: LICENSE
Classifier: Programming Language :: Python :: 3
Classifier: Operating System :: OS Independent
Requires-Python: >=3.9
Project-URL: Homepage, https://github.com/Orange23333/tfwr-expand
Project-URL: Issues, https://github.com/Orange23333/tfwr-expand/issues
